{
"type": "FeatureCollection",
"name": "hcr",
"crs": { "type": "name", "properties": { "name": "urn:ogc:def:crs:OGC:1.3:CRS84" } },
"features": [
{ "type": "Feature", "properties": { "id": 3, "name": "Hồ Con Rùa" }, "geometry": { "type": "Point", "coordinates": [ 106.695932073954623, 10.782660200760372 ] } }
]
}
