{
"type": "FeatureCollection",
"name": "ntdb",
"crs": { "type": "name", "properties": { "name": "urn:ogc:def:crs:OGC:1.3:CRS84" } },
"features": [
{ "type": "Feature", "properties": { "id": 4, "name": "Nhà thờ Đức Bà Sài Gòn" }, "geometry": { "type": "Point", "coordinates": [ 106.699069283215778, 10.779730124278355 ] } }
]
}
